{
  "anonymized": null,
  "callback_url": null,
  "class": "standard",
  "destaddr": "MOBILE",
  "encoding": "UTF8",
  "id": 2112080685,
  "label": null,
  "message": "should pass",
  "payload": null,
  "priority": "NORMAL",
  "recipients": [
    {
      "actual_sender": "SomeSender",
      "country": "HR",
      "csms": 1,
      "dsnerror": null,
      "dsnerrorcode": null,
      "dsnstatus": "DELIVERED",
      "dsntime": 1644707423.0,
      "mcc": null,
      "mnc": null,
      "msisdn": "385998653414",
      "senttime": 1644707416.0,
      "tagvalues": null
    }
  ],
  "sender": "SomeSender",
  "sendtime": null,
  "tags": null,
  "udh": null,
  "userref": null,
  "validity_period": null
}
